{
  "algo_version_pinned": "",
  "assignee": "",
  "category": "sleep",
  "data_freeze_policy": "",
  "deprecation_policy": "",
  "entry_id": "SLP-GLY-THERM",
  "evidence_tier": "P1",
  "final_tier": "Gold",
  "formulation_detail": "3g evening dosing with cooling protocol",
  "formulation_policy": "merge",
  "generated_version": "v1",
  "last_updated": "2024-05-01T00:00:00Z",
  "notes": "Track core body temperature change and morning alertness",
  "primary_indication": "sleep_latency",
  "priority": "medium",
  "source_hint": "PMID: 20110082",
  "status": "curated",
  "substance": "glycine"
}
