[
  {
    "entry_id": "SLP-THN-ALPHA",
    "category": "sleep",
    "substance": "l_theanine",
    "formulation_policy": "merge",
    "formulation_detail": "evening alpha-wave modulation",
    "primary_indication": "sleep_quality",
    "priority": "medium",
    "evidence_tier": "P1",
    "source_hint": "PMID: 32239622",
    "status": "pending",
    "assignee": "",
    "final_tier": "",
    "notes": "Segment adult anxiety cohorts vs healthy sleepers",
    "last_updated": "2024-05-01T00:00:00Z",
    "algo_version_pinned": "",
    "data_freeze_policy": "",
    "deprecation_policy": ""
  },
  {
    "entry_id": "SLP-TCH-TRP",
    "category": "sleep",
    "substance": "tart_cherry",
    "formulation_policy": "merge",
    "formulation_detail": "proanthocyanidin-rich concentrate",
    "primary_indication": "sleep_duration",
    "priority": "medium",
    "evidence_tier": "P1",
    "source_hint": "doi:10.1080/07315724.2012.10720465",
    "status": "pending",
    "assignee": "",
    "final_tier": "",
    "notes": "Differentiate juice vs extract capsules",
    "last_updated": "2024-05-01T00:00:00Z",
    "algo_version_pinned": "",
    "data_freeze_policy": "",
    "deprecation_policy": ""
  },
  {
    "entry_id": "SLP-LEM-TRANQ",
    "category": "sleep",
    "substance": "lemon_balm",
    "formulation_policy": "merge",
    "formulation_detail": "rosmarinic acid standardization",
    "primary_indication": "sleep_quality",
    "priority": "low",
    "evidence_tier": "P1",
    "source_hint": "PMID: 23724484",
    "status": "pending",
    "assignee": "",
    "final_tier": "",
    "notes": "Track daytime calmness spillover",
    "last_updated": "2024-05-01T00:00:00Z",
    "algo_version_pinned": "",
    "data_freeze_policy": "",
    "deprecation_policy": ""
  },
  {
    "entry_id": "MENT-OMEGA-MOOD",
    "category": "mental_health",
    "substance": "omega_3",
    "formulation_policy": "merge",
    "formulation_detail": "EPA dominant formulations for mood",
    "primary_indication": "depression",
    "priority": "high",
    "evidence_tier": "P0",
    "source_hint": "doi:10.1001/jama.2018.8047",
    "status": "pending",
    "assignee": "",
    "final_tier": "",
    "notes": "Flag trials with EPA:DHA >= 2:1",
    "last_updated": "2024-05-01T00:00:00Z",
    "algo_version_pinned": "",
    "data_freeze_policy": "",
    "deprecation_policy": ""
  },
  {
    "entry_id": "MENT-SAM-E",
    "category": "mental_health",
    "substance": "sam_e",
    "formulation_policy": "merge",
    "formulation_detail": "stabilized enteric coated",
    "primary_indication": "depression",
    "priority": "high",
    "evidence_tier": "P0",
    "source_hint": "PMID: 29247382",
    "status": "pending",
    "assignee": "",
    "final_tier": "",
    "notes": "Capture adjunct SSRI protocols",
    "last_updated": "2024-05-01T00:00:00Z",
    "algo_version_pinned": "",
    "data_freeze_policy": "",
    "deprecation_policy": ""
  },
  {
    "entry_id": "MENT-STJ-WORT",
    "category": "mental_health",
    "substance": "st_johns_wort",
    "formulation_policy": "split",
    "formulation_detail": "hypericin titration",
    "primary_indication": "depression",
    "priority": "high",
    "evidence_tier": "P0",
    "source_hint": "PMID: 28756543",
    "status": "pending",
    "assignee": "",
    "final_tier": "",
    "notes": "Document CYP interactions",
    "last_updated": "2024-05-01T00:00:00Z",
    "algo_version_pinned": "",
    "data_freeze_policy": "",
    "deprecation_policy": ""
  },
  {
    "entry_id": "COG-LION-NEURO",
    "category": "cognition",
    "substance": "lions_mane",
    "formulation_policy": "merge",
    "formulation_detail": "hericenone vs erinacine",
    "primary_indication": "cognitive_decline",
    "priority": "high",
    "evidence_tier": "P0",
    "source_hint": "PMID: 24266378",
    "status": "pending",
    "assignee": "",
    "final_tier": "",
    "notes": "Separate dementia vs mild impairment cohorts",
    "last_updated": "2024-05-01T00:00:00Z",
    "algo_version_pinned": "",
    "data_freeze_policy": "",
    "deprecation_policy": ""
  },
  {
    "entry_id": "COG-ALPGPC-FOCUS",
    "category": "cognition",
    "substance": "alpha_gpc",
    "formulation_policy": "merge",
    "formulation_detail": "cognitive enhancement",
    "primary_indication": "attention",
    "priority": "medium",
    "evidence_tier": "P1",
    "source_hint": "PMID: 23909254",
    "status": "pending",
    "assignee": "",
    "final_tier": "",
    "notes": "Include stroke recovery data",
    "last_updated": "2024-05-01T00:00:00Z",
    "algo_version_pinned": "",
    "data_freeze_policy": "",
    "deprecation_policy": ""
  },
  {
    "entry_id": "COG-ACET-LEARN",
    "category": "cognition",
    "substance": "acetyl_l_carnitine",
    "formulation_policy": "merge",
    "formulation_detail": "neuroplasticity stack",
    "primary_indication": "processing_speed",
    "priority": "medium",
    "evidence_tier": "P1",
    "source_hint": "PMID: 24316276",
    "status": "pending",
    "assignee": "",
    "final_tier": "",
    "notes": "Flag combination with alpha lipoic acid",
    "last_updated": "2024-05-01T00:00:00Z",
    "algo_version_pinned": "",
    "data_freeze_policy": "",
    "deprecation_policy": ""
  },
  {
    "entry_id": "CARD-OMEGA-CARD",
    "category": "cardiovascular",
    "substance": "omega_3",
    "formulation_policy": "split",
    "formulation_detail": "EPA vs EPA+DHA cardiovascular",
    "primary_indication": "triglycerides",
    "priority": "high",
    "evidence_tier": "P0",
    "source_hint": "PMID: 31475798",
    "status": "pending",
    "assignee": "",
    "final_tier": "",
    "notes": "Stratify REDUCE-IT style protocols",
    "last_updated": "2024-05-01T00:00:00Z",
    "algo_version_pinned": "",
    "data_freeze_policy": "",
    "deprecation_policy": ""
  },
  {
    "entry_id": "CARD-REDY-STATIN",
    "category": "cardiovascular",
    "substance": "red_yeast_rice",
    "formulation_policy": "split",
    "formulation_detail": "monacolin K content",
    "primary_indication": "cholesterol",
    "priority": "high",
    "evidence_tier": "P1",
    "source_hint": "PMID: 27826854",
    "status": "pending",
    "assignee": "",
    "final_tier": "",
    "notes": "Flag statin-equivalent dosing",
    "last_updated": "2024-05-01T00:00:00Z",
    "algo_version_pinned": "",
    "data_freeze_policy": "",
    "deprecation_policy": ""
  },
  {
    "entry_id": "CARD-POLY-RES",
    "category": "cardiovascular",
    "substance": "polyphenol_blend",
    "formulation_policy": "merge",
    "formulation_detail": "grape seed + resveratrol",
    "primary_indication": "blood_pressure",
    "priority": "low",
    "evidence_tier": "P1",
    "source_hint": "PMID: 26608248",
    "status": "pending",
    "assignee": "",
    "final_tier": "",
    "notes": "Confirm blend composition",
    "last_updated": "2024-05-01T00:00:00Z",
    "algo_version_pinned": "",
    "data_freeze_policy": "",
    "deprecation_policy": ""
  },
  {
    "entry_id": "IMM-IMM03",
    "category": "immune",
    "substance": "vitamin_c",
    "formulation_policy": "split",
    "formulation_detail": "standardized protocol 3",
    "primary_indication": "antiviral_support",
    "priority": "medium",
    "evidence_tier": "P1",
    "source_hint": "PMID: 711003",
    "status": "pending",
    "assignee": "automation",
    "final_tier": "",
    "notes": "stub rollback @2025-11-05; Document immune outcomes for vitamin_c cohort 3\nBatch generated on 2025-10-24T08:19:09.701680+00:00",
    "last_updated": "2025-10-24T08:19:09.701728",
    "algo_version_pinned": "",
    "data_freeze_policy": "",
    "deprecation_policy": ""
  },
  {
    "entry_id": "IMM-IMM04",
    "category": "immune",
    "substance": "vitamin_d",
    "formulation_policy": "merge",
    "formulation_detail": "standardized protocol 4",
    "primary_indication": "upper_respiratory",
    "priority": "low",
    "evidence_tier": "P2",
    "source_hint": "PMID: 711004",
    "status": "pending",
    "assignee": "automation",
    "final_tier": "",
    "notes": "stub rollback @2025-11-05; Document immune outcomes for vitamin_d cohort 4\nBatch generated on 2025-10-24T08:19:09.825189+00:00",
    "last_updated": "2025-10-24T08:19:09.825243",
    "algo_version_pinned": "",
    "data_freeze_policy": "",
    "deprecation_policy": ""
  },
  {
    "entry_id": "IMM-IMM07",
    "category": "immune",
    "substance": "beta_glucans",
    "formulation_policy": "merge",
    "formulation_detail": "standardized protocol 7",
    "primary_indication": "antiviral_support",
    "priority": "medium",
    "evidence_tier": "P1",
    "source_hint": "PMID: 711007",
    "status": "pending",
    "assignee": "automation",
    "final_tier": "",
    "notes": "stub rollback @2025-11-05; Document immune outcomes for beta_glucans cohort 7\nBatch generated on 2025-10-24T08:19:10.199553+00:00",
    "last_updated": "2025-10-24T08:19:10.199601",
    "algo_version_pinned": "",
    "data_freeze_policy": "",
    "deprecation_policy": ""
  },
  {
    "entry_id": "META-GLU02",
    "category": "metabolic",
    "substance": "alpha_lipoic_acid",
    "formulation_policy": "merge",
    "formulation_detail": "standardized protocol 2",
    "primary_indication": "insulin_sensitivity",
    "priority": "medium",
    "evidence_tier": "P1",
    "source_hint": "PMID: 371002",
    "status": "pending",
    "assignee": "automation",
    "final_tier": "",
    "notes": "stub rollback @2025-11-05; Document metabolic outcomes for alpha_lipoic_acid protocol 2\nBatch generated on 2025-10-24T08:19:07.137967+00:00",
    "last_updated": "2025-10-24T08:19:07.138030",
    "algo_version_pinned": "",
    "data_freeze_policy": "",
    "deprecation_policy": ""
  },
  {
    "entry_id": "META-GLU06",
    "category": "metabolic",
    "substance": "bitter_melon",
    "formulation_policy": "split",
    "formulation_detail": "standardized protocol 6",
    "primary_indication": "glucose_control",
    "priority": "medium",
    "evidence_tier": "P1",
    "source_hint": "PMID: 371006",
    "status": "pending",
    "assignee": "automation",
    "final_tier": "",
    "notes": "stub rollback @2025-11-05; Document metabolic outcomes for bitter_melon protocol 6\nBatch generated on 2025-10-24T08:19:07.611183+00:00",
    "last_updated": "2025-10-24T08:19:07.611225",
    "algo_version_pinned": "",
    "data_freeze_policy": "",
    "deprecation_policy": ""
  },
  {
    "entry_id": "META-GLU09",
    "category": "metabolic",
    "substance": "vanadyl_sulfate",
    "formulation_policy": "split",
    "formulation_detail": "standardized protocol 9",
    "primary_indication": "weight_management",
    "priority": "high",
    "evidence_tier": "P0",
    "source_hint": "PMID: 371009",
    "status": "pending",
    "assignee": "automation",
    "final_tier": "",
    "notes": "stub rollback @2025-11-05; Document metabolic outcomes for vanadyl_sulfate protocol 9\nBatch generated on 2025-10-24T08:19:07.941002+00:00",
    "last_updated": "2025-10-24T08:19:07.941039",
    "algo_version_pinned": "",
    "data_freeze_policy": "",
    "deprecation_policy": ""
  },
  {
    "entry_id": "INFL-INF03",
    "category": "inflammation",
    "substance": "omega_3",
    "formulation_policy": "split",
    "formulation_detail": "standardized protocol 3",
    "primary_indication": "recovery",
    "priority": "medium",
    "evidence_tier": "P1",
    "source_hint": "PMID: 451003",
    "status": "pending",
    "assignee": "automation",
    "final_tier": "",
    "notes": "stub rollback @2025-11-05; Track inflammatory biomarkers for omega_3 entry 3\nStub entry generated on 2025-10-27T01:51:32.536126+00:00",
    "last_updated": "2025-10-27T01:51:32.536132+00:00",
    "algo_version_pinned": "",
    "data_freeze_policy": "",
    "deprecation_policy": ""
  },
  {
    "entry_id": "INFL-INF04",
    "category": "inflammation",
    "substance": "ginger",
    "formulation_policy": "merge",
    "formulation_detail": "standardized protocol 4",
    "primary_indication": "joint_pain",
    "priority": "low",
    "evidence_tier": "P2",
    "source_hint": "PMID: 451004",
    "status": "pending",
    "assignee": "",
    "final_tier": "",
    "notes": "Track inflammatory biomarkers for ginger entry 4",
    "last_updated": "2024-05-01T00:00:00Z",
    "algo_version_pinned": "",
    "data_freeze_policy": "",
    "deprecation_policy": ""
  },
  {
    "entry_id": "INFL-INF07",
    "category": "inflammation",
    "substance": "green_tea",
    "formulation_policy": "merge",
    "formulation_detail": "standardized protocol 7",
    "primary_indication": "systemic_inflammation",
    "priority": "medium",
    "evidence_tier": "P1",
    "source_hint": "PMID: 451007",
    "status": "pending",
    "assignee": "automation",
    "final_tier": "",
    "notes": "stub rollback @2025-11-05; Track inflammatory biomarkers for green_tea entry 7\nStub entry generated on 2025-10-27T01:51:32.540789+00:00",
    "last_updated": "2025-10-27T01:51:32.540797+00:00",
    "algo_version_pinned": "",
    "data_freeze_policy": "",
    "deprecation_policy": ""
  },
  {
    "entry_id": "LONG-LON01",
    "category": "longevity",
    "substance": "nicotinamide_riboside",
    "formulation_policy": "merge",
    "formulation_detail": "standardized protocol 1",
    "primary_indication": "cellular_ageing",
    "priority": "high",
    "evidence_tier": "P0",
    "source_hint": "PMID: 521001",
    "status": "pending",
    "assignee": "automation",
    "final_tier": "",
    "notes": "stub rollback @2025-11-05; Summarize longevity markers for nicotinamide_riboside study 1\nStub entry generated on 2025-10-27T01:51:32.555903+00:00",
    "last_updated": "2025-10-27T01:51:32.555911+00:00",
    "algo_version_pinned": "",
    "data_freeze_policy": "",
    "deprecation_policy": ""
  },
  {
    "entry_id": "LONG-LON02",
    "category": "longevity",
    "substance": "nicotinamide_mononucleotide",
    "formulation_policy": "merge",
    "formulation_detail": "standardized protocol 2",
    "primary_indication": "mitochondrial_function",
    "priority": "medium",
    "evidence_tier": "P1",
    "source_hint": "PMID: 521002",
    "status": "pending",
    "assignee": "automation",
    "final_tier": "",
    "notes": "stub rollback @2025-11-05; Summarize longevity markers for nicotinamide_mononucleotide study 2\nStub entry generated on 2025-10-27T01:51:32.557674+00:00",
    "last_updated": "2025-10-27T01:51:32.557684+00:00",
    "algo_version_pinned": "",
    "data_freeze_policy": "",
    "deprecation_policy": ""
  },
  {
    "entry_id": "LONG-LON04",
    "category": "longevity",
    "substance": "pterostilbene",
    "formulation_policy": "merge",
    "formulation_detail": "standardized protocol 4",
    "primary_indication": "cellular_ageing",
    "priority": "low",
    "evidence_tier": "P2",
    "source_hint": "PMID: 521004",
    "status": "pending",
    "assignee": "",
    "final_tier": "",
    "notes": "Summarize longevity markers for pterostilbene study 4",
    "last_updated": "2024-05-01T00:00:00Z",
    "algo_version_pinned": "",
    "data_freeze_policy": "",
    "deprecation_policy": ""
  },
  {
    "entry_id": "ENDO-END01",
    "category": "endocrine",
    "substance": "inositol",
    "formulation_policy": "merge",
    "formulation_detail": "standardized protocol 1",
    "primary_indication": "pcos_support",
    "priority": "high",
    "evidence_tier": "P0",
    "source_hint": "PMID: 821001",
    "status": "pending",
    "assignee": "",
    "final_tier": "",
    "notes": "Capture endocrine metrics for inositol case 1",
    "last_updated": "2024-05-01T00:00:00Z",
    "algo_version_pinned": "",
    "data_freeze_policy": "",
    "deprecation_policy": ""
  },
  {
    "entry_id": "ENDO-END02",
    "category": "endocrine",
    "substance": "berberine",
    "formulation_policy": "merge",
    "formulation_detail": "standardized protocol 2",
    "primary_indication": "thyroid_support",
    "priority": "medium",
    "evidence_tier": "P1",
    "source_hint": "PMID: 821002",
    "status": "pending",
    "assignee": "",
    "final_tier": "",
    "notes": "Capture endocrine metrics for berberine case 2",
    "last_updated": "2024-05-01T00:00:00Z",
    "algo_version_pinned": "",
    "data_freeze_policy": "",
    "deprecation_policy": ""
  },
  {
    "entry_id": "GUT-PROBIO-SCFAs",
    "category": "gut_health",
    "substance": "probiotic_blend",
    "formulation_policy": "merge",
    "formulation_detail": "multi strain scfa production optimization",
    "primary_indication": "short_chain_fatty_acids",
    "priority": "medium",
    "evidence_tier": "P1",
    "source_hint": "PMID: 35824610",
    "status": "pending",
    "assignee": "",
    "final_tier": "",
    "notes": "Pair metabolomics with symptom relief indices",
    "last_updated": "2025-02-19T00:00:00Z",
    "algo_version_pinned": "",
    "data_freeze_policy": "",
    "deprecation_policy": ""
  },
  {
    "entry_id": "GUT-PREBIO-BLOAT",
    "category": "gut_health",
    "substance": "prebiotic_fiber",
    "formulation_policy": "split",
    "formulation_detail": "phgg vs partially hydrolyzed guar gum",
    "primary_indication": "bloating_relief",
    "priority": "medium",
    "evidence_tier": "P1",
    "source_hint": "PMID: 33759192",
    "status": "pending",
    "assignee": "",
    "final_tier": "",
    "notes": "Track fermentation tolerance windows",
    "last_updated": "2025-02-19T00:00:00Z",
    "algo_version_pinned": "",
    "data_freeze_policy": "",
    "deprecation_policy": ""
  },
  {
    "entry_id": "IMM-BCP-IMM",
    "category": "immune_health",
    "substance": "black_cumin_seed",
    "formulation_policy": "merge",
    "formulation_detail": "thymoquinone rich oil",
    "primary_indication": "immune_modulation",
    "priority": "medium",
    "evidence_tier": "P1",
    "source_hint": "PMID: 35295041",
    "status": "pending",
    "assignee": "automation",
    "final_tier": "",
    "notes": "stub rollback @2025-11-05; Align cytokine profiling with clinical outcomes\nBatch generated on 2025-10-24T08:19:12.658006+00:00",
    "last_updated": "2025-10-24T08:19:12.658087",
    "algo_version_pinned": "",
    "data_freeze_policy": "",
    "deprecation_policy": ""
  },
  {
    "entry_id": "IMM-BETA-GLUC",
    "category": "immune_health",
    "substance": "beta_glucan",
    "formulation_policy": "merge",
    "formulation_detail": "yeast derived vs mushroom derived",
    "primary_indication": "immune_readiness",
    "priority": "medium",
    "evidence_tier": "P1",
    "source_hint": "PMID: 32589619",
    "status": "pending",
    "assignee": "automation",
    "final_tier": "",
    "notes": "stub rollback @2025-11-05; Include innate immunity assays and vaccine response data\nStub entry generated on 2025-10-27T01:50:36.319480+00:00",
    "last_updated": "2025-10-27T01:50:36.319490+00:00",
    "algo_version_pinned": "",
    "data_freeze_policy": "",
    "deprecation_policy": ""
  }
]