{
  "generated": "2025-11-06T07:17:04.343426+00:00",
  "policy_fingerprint": "0x6036438e1b958d88",
  "source_evidence": "entries/physiological/chondroitin-musc-msk03/musculoskeletal/v1/evidence.csv",
  "preferred_citation": "Kim G. TERVYX Protocol v1.0 (2025).",
  "studies": [
    {
      "study_id": "MUSC-MSK03_01",
      "year": 2016,
      "design": "randomized controlled trial",
      "journal": "musculoskeletal_journal",
      "outcome": "muscle_recovery",
      "population": "Adults with muscle recovery concerns",
      "adverse_events": "None reported",
      "doi": "10.1234/chondroitin-musc-msk03-01",
      "url": "https://doi.org/10.1234/chondroitin-musc-msk03-01",
      "citation": "MUSC-MSK03_01 (2016); Journal: musculoskeletal_journal; Design: randomized controlled trial; Population: Adults with muscle recovery concerns; Outcome: muscle_recovery; DOI: 10.1234/chondroitin-musc-msk03-01; Adverse Events: None reported."
    },
    {
      "study_id": "MUSC-MSK03_02",
      "year": 2017,
      "design": "randomized controlled trial",
      "journal": "musculoskeletal_journal",
      "outcome": "muscle_recovery",
      "population": "Adults with muscle recovery concerns",
      "adverse_events": "Mild GI discomfort",
      "doi": "10.1234/chondroitin-musc-msk03-02",
      "url": "https://doi.org/10.1234/chondroitin-musc-msk03-02",
      "citation": "MUSC-MSK03_02 (2017); Journal: musculoskeletal_journal; Design: randomized controlled trial; Population: Adults with muscle recovery concerns; Outcome: muscle_recovery; DOI: 10.1234/chondroitin-musc-msk03-02; Adverse Events: Mild GI discomfort."
    },
    {
      "study_id": "MUSC-MSK03_03",
      "year": 2018,
      "design": "randomized controlled trial",
      "journal": "musculoskeletal_journal",
      "outcome": "muscle_recovery",
      "population": "Adults with muscle recovery concerns",
      "adverse_events": "Mild GI discomfort",
      "doi": "10.1234/chondroitin-musc-msk03-03",
      "url": "https://doi.org/10.1234/chondroitin-musc-msk03-03",
      "citation": "MUSC-MSK03_03 (2018); Journal: musculoskeletal_journal; Design: randomized controlled trial; Population: Adults with muscle recovery concerns; Outcome: muscle_recovery; DOI: 10.1234/chondroitin-musc-msk03-03; Adverse Events: Mild GI discomfort."
    }
  ],
  "references": [
    {
      "type": "doi",
      "identifier": "10.1234/chondroitin-musc-msk03-01",
      "study_ids": [
        "MUSC-MSK03_01"
      ],
      "primary_study_id": "MUSC-MSK03_01",
      "url": "https://doi.org/10.1234/chondroitin-musc-msk03-01"
    },
    {
      "type": "doi",
      "identifier": "10.1234/chondroitin-musc-msk03-02",
      "study_ids": [
        "MUSC-MSK03_02"
      ],
      "primary_study_id": "MUSC-MSK03_02",
      "url": "https://doi.org/10.1234/chondroitin-musc-msk03-02"
    },
    {
      "type": "doi",
      "identifier": "10.1234/chondroitin-musc-msk03-03",
      "study_ids": [
        "MUSC-MSK03_03"
      ],
      "primary_study_id": "MUSC-MSK03_03",
      "url": "https://doi.org/10.1234/chondroitin-musc-msk03-03"
    }
  ],
  "manifest_hash": "sha256:e583efb66041216f188d1d73200f3b73562302b36d1b49ef9abff0f3ff011878"
}
